stablehorde_api/__init__.py
stablehorde_api/client.py
stablehorde_api/errors.py
stablehorde_api/models.py
stablehordeapi_py-0.1.0.dist-info/LICENSE
stablehordeapi_py-0.1.0.dist-info/METADATA
stablehordeapi_py-0.1.0.dist-info/WHEEL
stablehordeapi_py-0.1.0.dist-info/RECORD
