Metadata-Version: 2.1
Name: stablehordeapi-py
Version: 0.1.0
Summary: Library for using Stable Horde API in Python
Home-page: https://github.com/timius100/StableHordeAPI.py
License: MIT
Keywords: stablehorde,async,asyncio
Author: Timur Bogdanov
Author-email: timurbogdanov2008@gmail.com
Requires-Python: >=3.8,<4.0
Classifier: Environment :: Console
Classifier: Intended Audience :: Developers
Classifier: License :: OSI Approved :: MIT License
Classifier: Programming Language :: Python :: 3
Classifier: Programming Language :: Python :: 3.8
Classifier: Programming Language :: Python :: 3.9
Classifier: Programming Language :: Python :: 3.10
Classifier: Programming Language :: Python :: 3.11
Classifier: Programming Language :: Python :: 3.10
Classifier: Programming Language :: Python :: 3.11
Classifier: Programming Language :: Python :: 3.8
Classifier: Programming Language :: Python :: 3.9
Classifier: Topic :: Software Development :: Libraries :: Python Modules
Classifier: Typing :: Typed
Requires-Dist: aiofiles (>=22.1.0,<23.0.0)
Requires-Dist: aiohttp (>=3.8.3,<4.0.0)
Requires-Dist: loguru (>=0.6.0,<0.7.0)
Requires-Dist: msgspec (>=0.10.1,<0.11.0)
Project-URL: Repository, https://github.com/timius100/StableHordeAPI.py
